speedcopy/__init__.py
speedcopy/fstatfs.py
speedcopy/version.py
speedcopy-2.1.5.dist-info/LICENSE
speedcopy-2.1.5.dist-info/METADATA
speedcopy-2.1.5.dist-info/WHEEL
speedcopy-2.1.5.dist-info/top_level.txt
speedcopy-2.1.5.dist-info/RECORD
